{
  "sequences": {
    "akdcah_seq": 300,
    "akdcsg_seq": 300,
    "akdchydnch_seq": 346,
    "akdchydbal_seq": 338,
    "akdchydbvg_seq": 300,
    "bddcah_seq": 300,
    "bddcsg_seq": 300,
    "sbdcah_seq": 300,
    "sbdcsg_seq": 300,
    "bddchydbal_seq": 373,
    "bddchydsan_seq": 323,
    "akdchydsan_seq": 311,
    "bddchydnch_seq": 374
  },
  "last_updated": "2025-12-06T16:52:11.139706",
  "version": "1.0",
  "bddchydbal_seq_history": [
    {
      "value": 364,
      "timestamp": "2025-12-06T16:40:53.066094"
    },
    {
      "value": 365,
      "timestamp": "2025-12-06T16:40:54.607460"
    },
    {
      "value": 366,
      "timestamp": "2025-12-06T16:40:56.122922"
    },
    {
      "value": 367,
      "timestamp": "2025-12-06T16:40:57.526242"
    },
    {
      "value": 368,
      "timestamp": "2025-12-06T16:40:59.040174"
    },
    {
      "value": 369,
      "timestamp": "2025-12-06T16:41:00.491910"
    },
    {
      "value": 370,
      "timestamp": "2025-12-06T16:41:01.869212"
    },
    {
      "value": 371,
      "timestamp": "2025-12-06T16:41:03.496735"
    },
    {
      "value": 372,
      "timestamp": "2025-12-06T16:41:05.000356"
    },
    {
      "value": 373,
      "timestamp": "2025-12-06T16:41:06.597625"
    }
  ],
  "akdchydbal_seq_history": [
    {
      "value": 329,
      "timestamp": "2025-12-06T16:37:42.549479"
    },
    {
      "value": 330,
      "timestamp": "2025-12-06T16:37:43.926055"
    },
    {
      "value": 331,
      "timestamp": "2025-12-06T16:37:45.560026"
    },
    {
      "value": 332,
      "timestamp": "2025-12-06T16:37:47.075562"
    },
    {
      "value": 333,
      "timestamp": "2025-12-06T16:41:08.035835"
    },
    {
      "value": 334,
      "timestamp": "2025-12-06T16:41:09.444134"
    },
    {
      "value": 335,
      "timestamp": "2025-12-06T16:41:10.896049"
    },
    {
      "value": 336,
      "timestamp": "2025-12-06T16:41:12.235480"
    },
    {
      "value": 337,
      "timestamp": "2025-12-06T16:41:13.818188"
    },
    {
      "value": 338,
      "timestamp": "2025-12-06T16:41:15.530451"
    }
  ],
  "bddchydsan_seq_history": [
    {
      "value": 314,
      "timestamp": "2025-12-06T16:15:57.148054"
    },
    {
      "value": 315,
      "timestamp": "2025-12-06T16:15:58.674425"
    },
    {
      "value": 316,
      "timestamp": "2025-12-06T16:16:00.156894"
    },
    {
      "value": 317,
      "timestamp": "2025-12-06T16:16:01.654465"
    },
    {
      "value": 318,
      "timestamp": "2025-12-06T16:16:03.247439"
    },
    {
      "value": 319,
      "timestamp": "2025-12-06T16:16:04.960432"
    },
    {
      "value": 320,
      "timestamp": "2025-12-06T16:16:06.500713"
    },
    {
      "value": 321,
      "timestamp": "2025-12-06T16:16:07.951018"
    },
    {
      "value": 322,
      "timestamp": "2025-12-06T16:16:09.586091"
    },
    {
      "value": 323,
      "timestamp": "2025-12-06T16:16:11.131097"
    }
  ],
  "akdchydsan_seq_history": [
    {
      "value": 302,
      "timestamp": "2025-12-05T15:40:52.914316"
    },
    {
      "value": 303,
      "timestamp": "2025-12-05T15:40:54.463550"
    },
    {
      "value": 304,
      "timestamp": "2025-12-05T15:40:56.168390"
    },
    {
      "value": 305,
      "timestamp": "2025-12-05T15:40:57.864223"
    },
    {
      "value": 306,
      "timestamp": "2025-12-05T15:40:59.349147"
    },
    {
      "value": 307,
      "timestamp": "2025-12-06T16:16:12.492897"
    },
    {
      "value": 308,
      "timestamp": "2025-12-06T16:16:14.000249"
    },
    {
      "value": 309,
      "timestamp": "2025-12-06T16:16:15.574572"
    },
    {
      "value": 310,
      "timestamp": "2025-12-06T16:16:17.108162"
    },
    {
      "value": 311,
      "timestamp": "2025-12-06T16:16:18.703048"
    }
  ],
  "bddchydnch_seq_history": [
    {
      "value": 365,
      "timestamp": "2025-12-06T16:41:27.456955"
    },
    {
      "value": 366,
      "timestamp": "2025-12-06T16:41:29.005212"
    },
    {
      "value": 367,
      "timestamp": "2025-12-06T16:41:30.392417"
    },
    {
      "value": 368,
      "timestamp": "2025-12-06T16:41:31.873448"
    },
    {
      "value": 369,
      "timestamp": "2025-12-06T16:41:33.688206"
    },
    {
      "value": 370,
      "timestamp": "2025-12-06T16:41:35.174128"
    },
    {
      "value": 371,
      "timestamp": "2025-12-06T16:52:06.876802"
    },
    {
      "value": 372,
      "timestamp": "2025-12-06T16:52:08.330603"
    },
    {
      "value": 373,
      "timestamp": "2025-12-06T16:52:09.719450"
    },
    {
      "value": 374,
      "timestamp": "2025-12-06T16:52:11.139724"
    }
  ],
  "akdchydnch_seq_history": [
    {
      "value": 337,
      "timestamp": "2025-12-06T16:38:16.914080"
    },
    {
      "value": 338,
      "timestamp": "2025-12-06T16:38:18.437605"
    },
    {
      "value": 339,
      "timestamp": "2025-12-06T16:41:36.089147"
    },
    {
      "value": 340,
      "timestamp": "2025-12-06T16:41:37.593414"
    },
    {
      "value": 341,
      "timestamp": "2025-12-06T16:41:39.031035"
    },
    {
      "value": 342,
      "timestamp": "2025-12-06T16:41:40.697486"
    },
    {
      "value": 343,
      "timestamp": "2025-12-06T16:41:42.131363"
    },
    {
      "value": 344,
      "timestamp": "2025-12-06T16:41:43.612414"
    },
    {
      "value": 345,
      "timestamp": "2025-12-06T16:41:45.116839"
    },
    {
      "value": 346,
      "timestamp": "2025-12-06T16:41:46.602247"
    }
  ]
}